taiga_contrib_ldap_auth_ext/__init__.py
taiga_contrib_ldap_auth_ext/apps.py
taiga_contrib_ldap_auth_ext/connector.py
taiga_contrib_ldap_auth_ext/services.py
taiga_contrib_ldap_auth_ext-0.5.dist-info/AUTHORS.md
taiga_contrib_ldap_auth_ext-0.5.dist-info/LICENSE
taiga_contrib_ldap_auth_ext-0.5.dist-info/LICENSE.txt
taiga_contrib_ldap_auth_ext-0.5.dist-info/METADATA
taiga_contrib_ldap_auth_ext-0.5.dist-info/WHEEL
taiga_contrib_ldap_auth_ext-0.5.dist-info/top_level.txt
taiga_contrib_ldap_auth_ext-0.5.dist-info/RECORD
